{
    "04.-1.01(Aula)": {
        "days": {
            "Thursday": [
                {
                    "summary": "ZVM: 21.03._eComm.Camp",
                    "end": "18:00",
                    "begin": "09:00"
                }
            ],
            "Sunday": [
                {
                    "summary": "ZVM: 24.03._eComm.Camp",
                    "end": "18:00",
                    "begin": "09:00"
                }
            ],
            "Tuesday": [
                {
                    "summary": "Degle, S., JenAll: 19.03._AO/JenALL_Interbild/Vorb.",
                    "end": "18:00",
                    "begin": "09:00"
                }
            ],
            "Wednesday": [
                {
                    "summary": "Degle, S., JenAll: 20.03._AO/JenALL_Interbild",
                    "end": "18:00",
                    "begin": "09:00"
                }
            ],
            "Friday": [
                {
                    "summary": "ZVM: 22.03._eComm.Camp",
                    "end": "18:00",
                    "begin": "09:00"
                }
            ]
        },
        "id": "SPLUSCA96B6"
    },
    "04.00.34": {
        "days": {
            "Friday": [
                {
                    "summary": "Brunner: 22.03._Hispek Workshop",
                    "end": "13:00",
                    "begin": "08:00"
                }
            ]
        },
        "id": "SPLUS4833BC"
    },
    "04.00.01 (HS6)": {
        "days": {
            "Thursday": [
                {
                    "summary": "ZVM: 21.03._eComm.Camp",
                    "end": "18:00",
                    "begin": "09:00"
                }
            ],
            "Sunday": [
                {
                    "summary": "ZVM: 24.03._eComm.Camp",
                    "end": "18:00",
                    "begin": "09:00"
                }
            ],
            "Friday": [
                {
                    "summary": "ZVM: 22.03._eComm.Camp",
                    "end": "18:00",
                    "begin": "09:00"
                }
            ]
        },
        "id": "SPLUS40B576"
    },
    "04.00.08(CIM)": {
        "days": {
            "Tuesday": [
                {
                    "summary": "Pfaff SciTec: SciTec_Schlegel_Stud.einf./-vorb./S/01.8",
                    "end": "15:30",
                    "begin": "14:00"
                }
            ],
            "Monday": [
                {
                    "summary": "Pfaff SciTec: SciTec_Schlegel_Stud.einf./-vorb./S/01.7",
                    "end": "11:30",
                    "begin": "10:00"
                }
            ]
        },
        "id": "SPLUSCA9608"
    },
    "04.03.12": {
        "days": {
            "Thursday": [
                {
                    "summary": "ZVM: 21.03._eComm.Camp",
                    "end": "18:00",
                    "begin": "09:00"
                }
            ],
            "Sunday": [
                {
                    "summary": "ZVM: 24.03._eComm.Camp",
                    "end": "18:00",
                    "begin": "09:00"
                }
            ],
            "Friday": [
                {
                    "summary": "ZVM: 22.03._eComm.Camp",
                    "end": "18:00",
                    "begin": "09:00"
                }
            ]
        },
        "id": "SPLUS40B570"
    },
    "05.03.36": {
        "days": {
            "Tuesday": [
                {
                    "summary": "Staupendahl(SciTec): JenALL_LMT/S/01.03",
                    "end": "16:00",
                    "begin": "09:00"
                }
            ],
            "Friday": [
                {
                    "summary": "JenAll 3: JenALL_LMB/S/01.01",
                    "end": "18:30",
                    "begin": "11:30"
                }
            ],
            "Wednesday": [
                {
                    "summary": "Staupendahl(SciTec): JenALL_LMT/S/01.04",
                    "end": "16:00",
                    "begin": "09:00"
                }
            ],
            "Monday": [
                {
                    "summary": "Staupendahl(SciTec): JenALL_LMT/S/01.02",
                    "end": "16:00",
                    "begin": "09:00"
                }
            ]
        },
        "id": "SPLUSD17C38"
    },
    "04.03.11": {
        "days": {
            "Thursday": [
                {
                    "summary": "ZVM: 21.03._eComm.Camp",
                    "end": "18:00",
                    "begin": "09:00"
                }
            ],
            "Sunday": [
                {
                    "summary": "ZVM: 24.03._eComm.Camp",
                    "end": "18:00",
                    "begin": "09:00"
                }
            ],
            "Friday": [
                {
                    "summary": "ZVM: 22.03._eComm.Camp",
                    "end": "18:00",
                    "begin": "09:00"
                }
            ]
        },
        "id": "SPLUS9BD8AE"
    },
    "04.03.10": {
        "days": {
            "Thursday": [
                {
                    "summary": "ZVM: 21.03._eComm.Camp",
                    "end": "18:00",
                    "begin": "09:00"
                }
            ],
            "Sunday": [
                {
                    "summary": "ZVM: 24.03._eComm.Camp",
                    "end": "18:00",
                    "begin": "09:00"
                }
            ],
            "Friday": [
                {
                    "summary": "ZVM: 22.03._eComm.Camp",
                    "end": "18:00",
                    "begin": "09:00"
                }
            ]
        },
        "id": "SPLUS412E9E"
    },
    "05.00.06": {
        "days": {
            "Thursday": [
                {
                    "summary": "Sickenberger: JenALL_AO-Sport-Optom./APL/01",
                    "end": "18:00",
                    "begin": "08:00"
                }
            ],
            "Sunday": [
                {
                    "summary": "JenAll: JenALL_AO-Bino-sehen/S/01.12",
                    "end": "18:00",
                    "begin": "09:00"
                }
            ],
            "Saturday": [
                {
                    "summary": "JenAll: JenALL_AO-Bino-sehen/S/01.11",
                    "end": "18:00",
                    "begin": "09:00"
                }
            ],
            "Friday": [
                {
                    "summary": "JenAll: JenALL_AO-Bino-sehen/S/01.10",
                    "end": "18:00",
                    "begin": "09:00"
                }
            ]
        },
        "id": "SPLUSD17C54"
    },
    "04.03.07": {
        "days": {
            "Thursday": [
                {
                    "summary": "ZVM: 21.03._eComm.Camp",
                    "end": "18:00",
                    "begin": "09:00"
                }
            ],
            "Sunday": [
                {
                    "summary": "ZVM: 24.03._eComm.Camp",
                    "end": "18:00",
                    "begin": "09:00"
                }
            ],
            "Friday": [
                {
                    "summary": "ZVM: 22.03._eComm.Camp",
                    "end": "18:00",
                    "begin": "09:00"
                }
            ]
        },
        "id": "SPLUS412E9D"
    }
}