{
    "04.-1.01(Aula)": {
        "days": {
            "Wednesday": [
                {
                    "end": "17:30",
                    "begin": "08:30",
                    "summary": "Lautenschläger, Haase: BW(BA)UPP/S/01.3"
                }
            ],
            "Monday": [
                {
                    "end": "17:30",
                    "begin": "08:30",
                    "summary": "Lautenschläger, Haase: BW(BA)UPP/S/01.1"
                }
            ],
            "Tuesday": [
                {
                    "end": "17:30",
                    "begin": "08:30",
                    "summary": "Lautenschläger, Haase: BW(BA)UPP/S/01.2"
                }
            ]
        },
        "id": "SPLUSCA96B6"
    }
}