{"05.00.03": {"days": {"Monday": [{"end": "12:00", "begin": "09:30", "summary": "H端bner: 11.09._H端bner_Verteidigung"}]}}, "05.00.04": {"days": {"Tuesday": [{"end": "11:30", "begin": "10:00", "summary": "Pollok, Munder, Nemitz: 12.09._Munder_Verteidigung"}], "Saturday": [{"end": "12:00", "begin": "09:00", "summary": "Stoetzer: JenALL/GM 2016/APL/02"}]}}, "01.02.12": {"days": {"Tuesday": [{"end": "20:00", "begin": "08:00", "summary": ": AG Bliedtner_3D Drucker Test_II"}], "Friday": [{"end": "20:00", "begin": "08:00", "summary": ": AG Bliedtner_3D Drucker Test_V"}], "Wednesday": [{"end": "20:00", "begin": "08:00", "summary": ": AG Bliedtner_3D Drucker Test_III"}], "Monday": [{"end": "20:00", "begin": "08:00", "summary": ": AG Bliedtner_3D Drucker Test_I"}], "Thursday": [{"end": "20:00", "begin": "08:00", "summary": ": AG Bliedtner_3D Drucker Test_IV"}]}}, "04.02.15": {"days": {"Wednesday": [{"end": "11:00", "begin": "09:30", "summary": "Feller: AG_Feller"}]}}, "05.03.36": {"days": {"Friday": [{"end": "18:00", "begin": "08:00", "summary": "Fleck: JenALL/TO/S/01.0"}]}}, "04.00.01(HS6)": {"days": {"Wednesday": [{"end": "09:00", "begin": "08:00", "summary": "Merker: 13.09._SciTec_Sch端ler"}, {"end": "11:00", "begin": "09:30", "summary": ": Sch端lerExpress/S/06"}]}}, "04.00.34": {"days": {"Tuesday": [{"end": "18:00", "begin": "08:30", "summary": "ZSB: STET_Lager/Packen Erstsem.beutel/02"}], "Thursday": [{"end": "18:00", "begin": "08:30", "summary": "ZSB: STET_Lager/Packen Erstsem.beutel/04"}], "Saturday": [{"end": "18:00", "begin": "08:30", "summary": "ZSB: STET_Lager/Packen Erstsem.beutel/06"}], "Wednesday": [{"end": "18:00", "begin": "08:30", "summary": "ZSB: STET_Lager/Packen Erstsem.beutel/03"}], "Monday": [{"end": "18:00", "begin": "08:30", "summary": "ZSB: STET_Lager/Packen Erstsem.beutel/01"}], "Friday": [{"end": "18:00", "begin": "08:30", "summary": "ZSB: STET_Lager/Packen Erstsem.beutel/05"}]}}, "05.00.10": {"days": {"Tuesday": [{"end": "11:30", "begin": "10:00", "summary": "Klier, Herrmann, Werner, C.: 12.09._MT_Vertdg."}], "Friday": [{"end": "16:30", "begin": "09:30", "summary": "Stoetzer: BW(BA)ABWL wiss.Arb.:Info-Rech., Aufb., Zitierw./S/01.3"}], "Wednesday": [{"end": "16:30", "begin": "09:30", "summary": "Stoetzer: BW(BA)ABWL wiss.Arb.:Info-Rech., Aufb., Zitierw./S/01.1"}], "Monday": [{"end": "11:30", "begin": "10:00", "summary": "Herrmann, Hoechstetter: 11.09._Herrmann/Vertdg."}], "Thursday": [{"end": "16:30", "begin": "09:30", "summary": "Stoetzer: BW(BA)ABWL wiss.Arb.:Info-Rech., Aufb., Zitierw./S/01.2"}]}}, "04.03.07": {"days": {"Tuesday": [{"end": "18:00", "begin": "08:00", "summary": "Bliedtner: JenALL/3-D-Druck/S/01.2"}], "Wednesday": [{"end": "18:00", "begin": "08:00", "summary": "Bliedtner: JenALL/3-D-Druck/S/01.3"}], "Monday": [{"end": "18:00", "begin": "08:00", "summary": "Bliedtner: JenALL/3-D-Druck/S/01.1"}], "Thursday": [{"end": "18:00", "begin": "08:00", "summary": "Bliedtner: JenALL/3-D-Druck/S/01.4"}]}}, "01.02.11": {"days": {"Tuesday": [{"end": "18:30", "begin": "08:30", "summary": ": Ref 4/Stuhllager/Senat/05"}], "Thursday": [{"end": "18:30", "begin": "08:30", "summary": ": Ref 4/Stuhllager/Senat/01"}], "Saturday": [{"end": "18:30", "begin": "08:30", "summary": ": Ref 4/Stuhllager/Senat/03"}], "Wednesday": [{"end": "18:30", "begin": "08:30", "summary": ": Ref 4/Stuhllager/Senat/06"}], "Monday": [{"end": "18:30", "begin": "08:30", "summary": ": Ref 4/Stuhllager/Senat/04"}], "Friday": [{"end": "18:30", "begin": "08:30", "summary": ": Ref 4/Stuhllager/Senat/02"}]}}, "04.00.10": {"days": {"Thursday": [{"end": "18:00", "begin": "08:00", "summary": "Bliedtner: JenALL/3-D-Druck/S/01.4"}]}}}